dalle_gen_save.py
dalle_gen_save-4.5.58.dist-info/METADATA
dalle_gen_save-4.5.58.dist-info/WHEEL
dalle_gen_save-4.5.58.dist-info/entry_points.txt
dalle_gen_save-4.5.58.dist-info/RECORD
