Metadata-Version: 2.3
Name: dalle_gen_save
Version: 4.5.58
Requires-Dist: openai
Requires-Dist: python-dotenv
